{
  "kind": "collectionType",
  "collectionName": "blogs",
  "info": {
    "singularName": "blog",
    "pluralName": "blogs",
    "displayName": "Post",
    "description": ""
  },
  "options": {
    "draftAndPublish": true
  },
  "pluginOptions": {},
  "attributes": {
    "blog": {
      "type": "richtext"
    },
    "title": {
      "type": "string"
    },
    "description": {
      "type": "text"
    },
    "categories": {
      "type": "relation",
      "relation": "manyToMany",
      "target": "api::category.category",
      "inversedBy": "blogs"
    },
    "cover": {
      "type": "media",
      "multiple": false,
      "required": false,
      "allowedTypes": [
        "images",
        "files",
        "videos",
        "audios"
      ]
    },
    "users_permissions_user": {
      "type": "relation",
      "relation": "manyToOne",
      "target": "plugin::users-permissions.user",
      "inversedBy": "posts"
    },
    "sources": {
      "type": "richtext"
    },
    "contnetArticle": {
      "type": "richtext"
    },
    "comments": {
      "type": "relation",
      "relation": "oneToMany",
      "target": "api::comment.comment"
    }
  }
}
